<?xml version="1.0" encoding="utf-8" ?>
<dwsync>
<file name="SpryMenuBarRight.gif" server="C:/wamp/www/agencedevoyage/" local="129884602739075091" remote="129884602730000000" />
<file name="SpryMenuBarRightHover.gif" server="C:/wamp/www/agencedevoyage/" local="129884602739095092" remote="129884602730000000" />
<file name="SpryMenuBar.js" server="C:/wamp/www/agencedevoyage/" local="129884602739055090" remote="129884602730000000" />
<file name="SpryMenuBarVertical.css" server="C:/wamp/www/agencedevoyage/" local="129924819149267930" remote="129924819140000000" />
<file name="SpryMenuBarDown.gif" server="C:/wamp/www/agencedevoyage/" local="129884610376881949" remote="129884610370000000" />
<file name="SpryMenuBarDownHover.gif" server="C:/wamp/www/agencedevoyage/" local="129884610376911951" remote="129884610370000000" />
<file name="SpryMenuBarHorizontal.css" server="C:/wamp/www/agencedevoyage/" local="129884610376951953" remote="129884610370000000" />
<file name="SpryValidationTextField.js" server="C:/wamp/www/agencedevoyage/" local="129927147419578163" remote="129927147410000000" />
<file name="SpryValidationTextField.css" server="C:/wamp/www/agencedevoyage/" local="129927147419368151" remote="129927147410000000" />
<file name="SpryValidationTextarea.js" server="C:/wamp/www/agencedevoyage/" local="129932957822021518" remote="129932957820000000" />
<file name="SpryValidationTextarea.css" server="C:/wamp/www/agencedevoyage/" local="129932957821881510" remote="129932957820000000" />
</dwsync>